{
  "schemaVersion": 1,
  "worldId": "survival-main",
  "worldVersion": 10,
  "worldChecksum": "FFB4C49DF1AA0A51B5EC4FF5A906314DAD078EDD990E015A63AC01D79CE59E01",
  "snapshotRef": "snapshots/survival-main/world-v000010.zip",
  "snapshotSizeBytes": 7589502,
  "status": "Hosting",
  "host": {
    "clientId": "40c879973bd34ca5ae283e5e7b841155",
    "displayName": "plane",
    "leaseId": "c8810f9f-1f44-43dd-98b6-b0f182e7f015",
    "leaseExpiresAtUtc": "2026-04-07T21:17:30.2917059+00:00",
    "lastHeartbeatUtc": "2026-04-07T21:16:45.2917057+00:00",
    "hostEpoch": 8
  },
  "lastUploadCompletedAtUtc": "2026-04-07T20:35:06.275862+00:00",
  "lastCompletedBy": "40c879973bd34ca5ae283e5e7b841155"
}